orgnized_cli/__init__.py
orgnized_cli/orgnized_cli.py
orgnized_cli-0.1.0.dist-info/METADATA
orgnized_cli-0.1.0.dist-info/WHEEL
orgnized_cli-0.1.0.dist-info/entry_points.txt
orgnized_cli-0.1.0.dist-info/RECORD
