Metadata-Version: 2.4
Name: orgnized-cli
Version: 0.1.0
Summary: A command-line tool for organizing files by type
Project-URL: Homepage, https://github.com/karvanpy/orgnized-cli
Project-URL: Bug Tracker, https://github.com/karvanpy/orgnized-cli/issues
Author-email: Ervan Kurniawan <ervankurniawan41@gmail.com>
Classifier: Development Status :: 3 - Alpha
Classifier: Intended Audience :: End Users/Desktop
Classifier: License :: OSI Approved :: MIT License
Classifier: Operating System :: OS Independent
Classifier: Programming Language :: Python :: 3
Classifier: Programming Language :: Python :: 3.8
Classifier: Programming Language :: Python :: 3.9
Classifier: Programming Language :: Python :: 3.10
Classifier: Programming Language :: Python :: 3.11
Requires-Python: >=3.8
